{
  "id": "5bc8b081626daf9c54d6129c",
  "type": "CodeStage",
  "containerId": "5bb2c8ded9f99705a60c62d3",
  "title": "Transfer Debt?",
  "position": 4,
  "validatedContract": "Token",
  "languageVersion": "0.1.0b3",
  "language": "vyper",
  "testFramework": "truffle_with_mocha",
  "updatedAt": "2018-10-25T16:54:07.515Z",
  "createdAt": "2018-10-18T16:10:41.057Z",
  "codeFileIds": [
    "5bc8b130626daf9c54d612a0",
    "5bb2d834d9f99705a60c6308"
  ],
  "task": "$$LOOKUP",
  "details": "$$LOOKUP",
  "completionMessage": "",
  "abiValidations": "$$LOOKUP"
}